totalsegmentator_konfai/__init__.py
totalsegmentator_konfai/cli.py
totalsegmentator_konfai-1.5.2.dist-info/licenses/LICENSE
totalsegmentator_konfai-1.5.2.dist-info/METADATA
totalsegmentator_konfai-1.5.2.dist-info/WHEEL
totalsegmentator_konfai-1.5.2.dist-info/entry_points.txt
totalsegmentator_konfai-1.5.2.dist-info/top_level.txt
totalsegmentator_konfai-1.5.2.dist-info/RECORD
