Metadata-Version: 2.4
Name: totalsegmentator-konfai
Version: 1.5.2
Summary: Fast and lightweight TotalSegmentator CLI powered by the KonfAI framework.
Author-email: Valentin Boussot <boussot.v@gmail.com>
License:                                  Apache License
Project-URL: Homepage, https://github.com/vboussot/KonfAI
Project-URL: Repository, https://github.com/vboussot/KonfAI
Project-URL: Issues, https://github.com/vboussot/KonfAI/issues
Project-URL: License, https://www.apache.org/licenses/LICENSE-2.0
Requires-Python: >=3.10
License-File: LICENSE
Requires-Dist: konfai==1.5.1
Dynamic: license-file
